vibrant_auth_middleware/__init__.py
vibrant_auth_middleware/config.py
vibrant_auth_middleware/dependencies.py
vibrant_auth_middleware/jwt_auth.py
vibrant_auth_middleware_fastapi-0.1.1.dist-info/METADATA
vibrant_auth_middleware_fastapi-0.1.1.dist-info/WHEEL
vibrant_auth_middleware_fastapi-0.1.1.dist-info/RECORD
