Metadata-Version: 2.4
Name: vibrant-auth-middleware-fastapi
Version: 0.1.1
Summary: FastAPI authentication middleware with JWT verification and Azure integration
Author-email: Vibrant Engineering <engineering@vibrant.com>
License: ISC
Requires-Python: >=3.11
Requires-Dist: azure-appconfiguration<2.0.0,>=1.7.0
Requires-Dist: azure-identity<2.0.0,>=1.15.0
Requires-Dist: azure-keyvault-secrets<5.0.0,>=4.8.0
Requires-Dist: fastapi>=0.100.0
Requires-Dist: python-jose[cryptography]<4.0.0,>=3.3.0
Provides-Extra: dev
Requires-Dist: pytest-asyncio<0.20.0,>=0.19.0; extra == 'dev'
Requires-Dist: pytest<8.0.0,>=7.1.2; extra == 'dev'
Requires-Dist: ruff<1.0.0,>=0.9.0; extra == 'dev'
